texttoapi/__init__.py
texttoapi/api_utils.py
texttoapi/chat_utils.py
texttoapi/cli_utils.py
texttoapi/env.py
texttoapi/llm.py
texttoapi/tracing.py
texttoapi/utils.py
texttoapi-0.1.5.dist-info/METADATA
texttoapi-0.1.5.dist-info/WHEEL
texttoapi-0.1.5.dist-info/top_level.txt
texttoapi-0.1.5.dist-info/RECORD
