Metadata-Version: 2.1
Name: texttoapi
Version: 0.1.5
Summary: A package for the TextToAPI tool
Author: Gopesh Sharma
Requires-Python: >=3.7
Requires-Dist: setuptools==75.6.0
Requires-Dist: python-dotenv==1.0.1
Requires-Dist: llama-index==0.12.1
Requires-Dist: llama-index-embeddings-azure-openai==0.3.0
Requires-Dist: llama-index-embeddings-bedrock==0.4.0
Requires-Dist: llama-index-llms-azure-openai==0.3.0
Requires-Dist: llama-index-llms-bedrock-converse==0.4.0
Requires-Dist: openinference-instrumentation-llama-index==3.0.4
Requires-Dist: opentelemetry-sdk==1.28.2
Requires-Dist: opentelemetry-exporter-otlp==1.28.2
Requires-Dist: opentelemetry-proto==1.28.2
Requires-Dist: rich==13.9.4
Requires-Dist: markdown2==2.5.2
Requires-Dist: Flask
